{
  "LEADS": [
    {
      "Name": "Nikit Mathur",
      "Designation": "Team Lead",
      "Facebook": "https://www.facebook.com/people/Nikit-Mathur/100082899335488/",
      "Linkedin": "https://www.linkedin.com/in/nikit-mathur-270033231/",
      "Instagram": "https://www.instagram.com/_nikitmathur_/"
    },
    {
      "Name": "Aarush Bhandari ",
      "Designation": "SAMBED Lead",
      "Linkedin": "https://www.linkedin.com/in/aarush-bhandari-33846326a/",
      "Instagram": "https://instagram.com/aarushbhandari4?igshid=ZDdkNTZiNTM=/"
    },
    {
      "Name": "Gokul Karthik Sai Vamshi",
      "Designation": "SIESED Lead",
      "Linkedin": "https://www.linkedin.com/in/gokul-karthik-492ab9252/",
      "Instagram": "https://instagram.com/__karthik__sai__?igshid=YmMyMTA2M2Y=/"
    },
    {
      "Name": "Divya Sai Aamuktha Pelluri",
      "Designation": "SPACED Lead",
      "Linkedin": "https://www.linkedin.com/in/divya-pelluri-1b8a1926b/",
      "Instagram": "https://www.instagram.com/ap29122003/"
    },
    {
      "Name": "Aryan Bali",
      "Designation": "MCSOCD Lead",
      "Linkedin": "https://www.linkedin.com/in/aryan-bali-a55615270/",
      "Instagram": "https://www.instagram.com/aryan12889/"
    }
  ],
  "SAMBED": [
    {
      "Name": "Ayush Goyal",
      "Designation": "Member",
      "Linkedin": "www.linkedin.com/in/ayush-goyal-4735a8230/",
      "Instagram": "https://instagram.com/ayush_goyal05?igshid=ZDdkNTZiNTM=/"
    },
    {
      "Name": "Gautam. M",
      "Designation": "Member",
      "Linkedin": "https://www.linkedin.com/in/gautam-m-770662259/",
      "Instagram": "https://instagram.com/m_gautam_14?igshid=ZDdkNTZiNTM=/"
    },
    {
      "Name": "Vijay Srikrishnan",
      "Designation": "Member",
      "Linkedin": "https://www.linkedin.com/in/vijay-srikrishnan-185323252/",
      "Instagram": "https://www.instagram.com/vijaysrikrishnan/"
    },
    {
      "Name": "Akhil Anil",
      "Designation": "Member",
      "Linkedin": "https://www.linkedin.com/in/akhil-anil-71ba81251/",
      "Instagram": "https://instagram.com/i_am_s_p_o_o_n?igshid=YmMyMTA2M2Y=/"
    },
    {
      "Name": "Amshu Kiran Belbase",
      "Designation": "Member",
      "Linkedin": "https://www.linkedin.com/in/amshu-belbase-727261245/",
      "Instagram": "https://www.instagram.com/amshubelbase08/"
    },
    {
      "Name": "Aniruddh Mathur",
      "Designation": "Member",
      "Linkedin": "https://www.linkedin.com/in/aniruddh-mathur-b1471b250/",
      "Instagram": "https://instagram.com/aniruddh.30?igshid=ZDdkNTZiNTM=/"
    },
    {
      "Name": "Sakshi K",
      "Designation": "Member"
    },
    {
      "Name": "Shohon Saha",
      "Designation": "Member",
      "Instagram": "https://instagram.com/earths_moon_?igshid=ZDdkNTZiNTM=/"
    },
    {
      "Name": "Siddhartha Sawant",
      "Designation": "Member",
      "Linkedin": "https://www.linkedin.com/in/siddhartha-sawant-185a55264/",
      "Instagram": "https://instagram.com/sidd.sawant_?igshid=ZDdkNTZiNTM=/"
    }
  ],
  "SIESED": [
    {
      "Name": "Deepak Sharda",
      "Designation": "Member",
      "Linkedin": "https://www.linkedin.com/in/deepak-sharda/",
      "Instagram": "https://instagram.com/deepak_sharda_?igshid=ZDdkNTZiNTM=/"
    },
    {
      "Name": "Smeet Bathani",
      "Designation": "Member",
      "Linkedin": "https://in.linkedin.com/in/smeet-bathani-2937b2226/",
      "Instagram": "https://www.instagram.com/_the_smeet_/"
    },
    {
      "Name": "Maheshwar M R",
      "Designation": "Member",
      "Linkedin": "https://www.linkedin.com/in/m-r-maheshwar-472305221/",
      "Instagram": "https://instagram.com/ateluguboy?igshid=YmMyMTA2M2Y=/"
    },
    {
      "Name": "Divjot Singh Manchanda",
      "Designation": "Member",
      "Linkedin": "https://www.linkedin.com/in/divjot-singh-manchanda-910643251/",
      "Instagram": "www.instagram.com/djsmanchanda/"
    },
    {
      "Name": "Krrish Verma",
      "Designation": "Member",
      "Linkedin": "https://www.linkedin.com/in/krrish-verma/",
      "Instagram": "https://instagram.com/krrish_verma__/"
    },
    {
      "Name": "Liya Maria Alex",
      "Designation": "Member",
      "Linkedin": "https://www.linkedin.com/in/liya-maria-alex-58817a24b/",
      "Instagram": "https://instagram.com/_m.liyx?igshid=ZDdkNTZiNTM=/"
    },
    {
      "Name": "Mohammed Sadriwala",
      "Designation": "Member",
      "Linkedin": "https://www.linkedin.com/in/mohammed-sadriwala-30205b25b/",
      "Instagram": "https://instagram.com/sadriwala_mohammed?igshid=ZDdkNTZiNTM=/"
    },
    {
      "Name": "Pracheta Mitra",
      "Designation": "Member",
      "Linkedin": "https://www.linkedin.com/in/pracheta-mitra-204409251/",
      "Instagram": "https://instagram.com/prach_was_here?igshid=ZDdkNTZiNTM=/"
    },
    {
      "Name": "Sanjeevini Mekin",
      "Designation": "Member",
      "Linkedin": "https://www.linkedin.com/in/sanjeevini-mekin-4403aa250",
      "Instagram": "https://instagram.com/sanjeevini_mekin/"
    },
    {
      "Name": "Tarushi Singh",
      "Designation": "Member",
      "Linkedin": "https://www.linkedin.com/in/tarushi-singh-1b655725b/",
      "Instagram": "https://instagram.com/httpt33?igshid=ZDdkNTZiNTM=/"
    }
  ],
  "SPACED": [
    {
      "Name": "Abhinav Raja Raizada",
      "Designation": "Member",
      "Linkedin": "https://www.linkedin.com/in/abhinav-raja-raizada-850440217/",
      "Instagram": "https://www.instagram.com/abhinnxvv/"
    },
    {
      "Name": "Diptayan Jash",
      "Designation": "Member",
      "Linkedin": "https://www.linkedin.com/in/diptayan-jash-63496b214/",
      "Instagram": "https://www.instagram.com/dj_dipt/"
    },
    {
      "Name": "Medhir Aryan",
      "Designation": "Member",
      "Linkedin": "https://www.linkedin.com/in/medhir-aryan-1b330826b/",
      "Instagram": "https://instagram.com/_.medhir._?igshid=YmMyMTA2M2Y=/"
    },
    {
      "Name": "Siddhima Singh",
      "Designation": "Member",
      "Linkedin": "https://linkedin.com/in/siddhima-singh-b9330226b/",
      "Instagram": "https://instagram.com/siddhu_paji__/"
    }
  ],
  "MCSOCD": [
    {
      "Name": "Abuzer Ganjifrockwala",
      "Designation": "Member",
      "Linkedin": "https://www.linkedin.com/in/abuzer-ganjifrockwala-9b5924226/",
      "Instagram": "https://instagram.com/abuzer_g63?igshid=YmMyMTA2M2Y=/"
    },
    {
      "Name": "Swetanshu Agrawal",
      "Designation": "Member",
      "Linkedin": "https://www.linkedin.com/in/swetanshu-agrawal/",
      "Instagram": "https://www.instagram.com/swetanshu.a/"
    },
    {
      "Name": "Harshita",
      "Designation": "Member",
      "Linkedin": "https://www.linkedin.com/in/harshita-kumari-0943b2242/",
      "Instagram": "https://instagram.com/harshita._.kumari?igshid=ZDdkNTZiNTM=/"
    },
    {
      "Name": "Maitry Parmar",
      "Designation": "Member",
      "Linkedin": "https://www.linkedin.com/in/maitry-parmar-8548ab251/",
      "Instagram": "https://instagram.com/maitryparmar_007?igshid=ZDdkNTZiNTM=/"
    },
    {
      "Name": "Shaurya Awasthi",
      "Designation": "Member",
      "Linkedin": "https://www.linkedin.com/in/shaurya-awashti-077034251/",
      "Instagram": "https://instagram.com/shaurya__awasthi192?igshid=ZDdkNTZiNTM=/"
    },
    {
      "Name": "Shreya Agrawal",
      "Designation": "Member",
      "Linkedin": "linkedin.com/in/shreya-agrawal-69a679243/",
      "Instagram": "https://www.instagram.com/shreyaagrawal04/"
    },
    {
      "Name": "Tamanna Grover",
      "Designation": "Member",
      "Linkedin": "https://www.linkedin.com/in/tamanna-grover-062b66252/",
      "Instagram": "https://www.instagram.com/tamanna.grover_/"
    },
    {
      "Name": "Vaibhav Raj",
      "Designation": "Member",
      "Linkedin": "https://www.linkedin.com/in/vaibhavraj-exe/",
      "Instagram": "https://instagram.com/vaibhavraj.exe?igshid=ZDdkNTZiNTM=/"
    }
  ],
  "MENTORS": [
    {
      "Name": "Roel Pais",
      "Designation": "Ex-Team Lead",
      "Linkedin": "https://www.linkedin.com/in/roel-pais-30b371223/",
      "Instagram": "https://www.instagram.com/roel_pais/"
    },
    {
      "Name": "Adheesh Mathur",
      "Designation": "Ex-SAMBED Lead",
      "Linkedin": "https://www.linkedin.com/in/adheesh-mathur-21b3ab241/",
      "Instagram": "https://instagram.com/_adheesh.1210_?igshid=ZDdkNTZiNTM=/"
    },
    {
      "Name": "Rehana",
      "Designation": "Ex-SIESED Lead"
    },
    {
      "Name": "Pranav Malakar",
      "Designation": "Ex-SPACED Lead",
      "Linkedin": "https://www.linkedin.com/in/pranav-malakar-bb6a2b156/"
    },
    {
      "Name": "Abishek.V",
      "Linkedin": "https://www.linkedin.com/in/abishek-lodha/",
      "Instagram": "https://www.instagram.com/abishek_lodha/"
    },
    {
      "Name": "Danush Ramakrishnan S",
      "Linkedin": "https://www.linkedin.com/in/danush-ramakrishnan-1913a1221/",
      "Instagram": "https://www.instagram.com/yumishiina_arts/"
    },
    {
      "Name": "Harikrishnan M",
      "Linkedin": "www.linkedin.com/in/harikrishnan-manoj",
      "Instagram": "https://www.instagram.com/_edwin_jarvis/"
    },
    {
      "Name": "Subham Pattanayak",
      "Linkedin": "https://www.linkedin.com/in/subham-pattanayak-b07b56237/",
      "Instagram": "https://instagram.com/_.subham2._?igshid=MTIzZWQxMDU=/"
    },
    {
      "Name": "Yakub Mathew",
      "Linkedin": "https://www.linkedin.com/in/yakub-mathew-7169621b6/",
      "Instagram": "https://www.instagram.com/yakub_mahew/"
    }
  ]
}